<?xml version="1.0" encoding="utf-8" ?>
<dwsync>
<file name="bootstrap.min.css" server="D:/WAMP/apache2/htdocs/" local="131659054198976995" remote="131659054190000000" Dst="2" />
<file name="bootstrap.min.js.download" server="D:/WAMP/apache2/htdocs/" local="131657299582095410" remote="131657299580000000" Dst="2" />
<file name="cover.css" server="D:/WAMP/apache2/htdocs/" local="131659055927898476" remote="131659055920000000" Dst="2" />
<file name="jquery-3.2.1.slim.min.js.download" server="D:/WAMP/apache2/htdocs/" local="131657299582120424" remote="131657299580000000" Dst="2" />
<file name="popper.min.js.download" server="D:/WAMP/apache2/htdocs/" local="131657299582125419" remote="131657299580000000" Dst="2" />
<file name="cover.css" server="C:/Users/shink/Documents/GitHub/GIMM300TeamSite/" local="131659055927898476" remote="131659055920000000" Dst="2" />
<file name="bootstrap.min.css" server="C:/Users/shink/Documents/GitHub/GIMM300TeamSite/" local="131659054198976995" remote="131659054190000000" Dst="2" />
<file name="bootstrap.min.js.download" server="C:/Users/shink/Documents/GitHub/GIMM300TeamSite/" local="131657299582095410" remote="131657299580000000" Dst="2" />
<file name="jquery-3.2.1.slim.min.js.download" server="C:/Users/shink/Documents/GitHub/GIMM300TeamSite/" local="131657299582120424" remote="131657299580000000" Dst="2" />
<file name="popper.min.js.download" server="C:/Users/shink/Documents/GitHub/GIMM300TeamSite/" local="131657299582125419" remote="131657299580000000" Dst="2" />
</dwsync>